icicle/Ghidra/Processors/6502/data/languages/6502.cspec
icicle/Ghidra/Processors/6502/data/languages/6502.ldefs
icicle/Ghidra/Processors/6502/data/languages/6502.pspec
icicle/Ghidra/Processors/6502/data/languages/6502.slaspec
icicle/Ghidra/Processors/6502/data/languages/65c02.slaspec
icicle/Ghidra/Processors/68000/data/languages/68000.cspec
icicle/Ghidra/Processors/68000/data/languages/68000.dwarf
icicle/Ghidra/Processors/68000/data/languages/68000.ldefs
icicle/Ghidra/Processors/68000/data/languages/68000.opinion
icicle/Ghidra/Processors/68000/data/languages/68000.pspec
icicle/Ghidra/Processors/68000/data/languages/68000.sinc
icicle/Ghidra/Processors/68000/data/languages/68000_register.cspec
icicle/Ghidra/Processors/68000/data/languages/68020.slaspec
icicle/Ghidra/Processors/68000/data/languages/68030.slaspec
icicle/Ghidra/Processors/68000/data/languages/68040.slaspec
icicle/Ghidra/Processors/68000/data/languages/coldfire.slaspec
icicle/Ghidra/Processors/8048/data/languages/8048.cspec
icicle/Ghidra/Processors/8048/data/languages/8048.ldefs
icicle/Ghidra/Processors/8048/data/languages/8048.pspec
icicle/Ghidra/Processors/8048/data/languages/8048.slaspec
icicle/Ghidra/Processors/8051/data/languages/80251.cspec
icicle/Ghidra/Processors/8051/data/languages/80251.pspec
icicle/Ghidra/Processors/8051/data/languages/80251.sinc
icicle/Ghidra/Processors/8051/data/languages/80251.slaspec
icicle/Ghidra/Processors/8051/data/languages/80390.cspec
icicle/Ghidra/Processors/8051/data/languages/80390.slaspec
icicle/Ghidra/Processors/8051/data/languages/8051.cspec
icicle/Ghidra/Processors/8051/data/languages/8051.ldefs
icicle/Ghidra/Processors/8051/data/languages/8051.pspec
icicle/Ghidra/Processors/8051/data/languages/8051.slaspec
icicle/Ghidra/Processors/8051/data/languages/8051_archimedes.cspec
icicle/Ghidra/Processors/8051/data/languages/8051_main.sinc
icicle/Ghidra/Processors/8051/data/languages/mx51.cspec
icicle/Ghidra/Processors/8051/data/languages/mx51.pspec
icicle_emu-0.0.11.dist-info/METADATA
icicle_emu-0.0.11.dist-info/WHEEL
icicle_emu-0.0.11.dist-info/licenses/LICENSE
icicle_emu-0.0.11.dist-info/RECORD
