Metadata-Version: 2.4
Name: icicle-emu
Version: 0.0.11
Classifier: License :: OSI Approved :: Boost Software License 1.0 (BSL-1.0)
Classifier: Intended Audience :: Developers
Classifier: Programming Language :: Python :: 3
Classifier: Development Status :: 5 - Production/Stable
Classifier: Operating System :: POSIX
Classifier: Operating System :: MacOS :: MacOS X
Classifier: Operating System :: Microsoft :: Windows
License-File: LICENSE
Summary: Python bindings for the Icicle emulator.
Requires-Python: >=3.8
Project-URL: Homepage, https://github.com/icicle-emu/icicle-python
Project-URL: Bug Tracker, https://github.com/icicle-emu/icicle-python/issues
